label_inspector/__init__.py
label_inspector/analysis/__init__.py
label_inspector/analysis/analysis_framework.py
label_inspector/analysis/char_analysis.py
label_inspector/analysis/confusable_grapheme_analysis.py
label_inspector/analysis/confusable_multi_grapheme_analysis.py
label_inspector/analysis/grapheme_analysis.py
label_inspector/analysis/grapheme_with_confusables_analysis.py
label_inspector/analysis/label_analysis.py
label_inspector/common/__init__.py
label_inspector/common/cache/label_inspector.common.myunicode.data.MyUnicodeData._data-0.pickle
label_inspector/common/cache/label_inspector.common.myunicode.grapheme.AllHanguls.hangul_jamo-0.pickle
label_inspector/common/cache/label_inspector.components.confusables.Confusables._full_confusable_graphemes-cf14b262710b6fe5432ff5737ae12cd2.pickle
label_inspector/common/cache/label_inspector.components.confusables.Confusables._simple_confusable_graphemes-cf14b262710b6fe5432ff5737ae12cd2.pickle
label_inspector/common/cache/label_inspector.components.font_support.FontSupport.supported-f9c51467fc626af5140dc6cb40441ddc.pickle
label_inspector/common/cache/label_inspector.components.font_support.FontSupport.unsupported-f9c51467fc626af5140dc6cb40441ddc.pickle
label_inspector/common/generate_cache.py
label_inspector/common/myunicode/__init__.py
label_inspector/common/myunicode/blocks.py
label_inspector/common/myunicode/data.py
label_inspector/common/myunicode/emojis.py
label_inspector/common/myunicode/grapheme.py
label_inspector/common/myunicode/myunicode.json
label_inspector/common/myunicode/myunicode.py
label_inspector/common/myunicode/scripts.py
label_inspector/common/myunicode/special.py
label_inspector/common/myunicode/utils.py
label_inspector/common/on_demand_regex.py
label_inspector/common/pickle_cache.py
label_inspector/common/punycode.py
label_inspector/components/__init__.py
label_inspector/components/confusables.py
label_inspector/components/features.py
label_inspector/components/font_support.py
ens_label_inspector-0.2.14.dist-info/LICENSE
ens_label_inspector-0.2.14.dist-info/METADATA
ens_label_inspector-0.2.14.dist-info/WHEEL
ens_label_inspector-0.2.14.dist-info/RECORD
