Metadata-Version: 2.1
Name: ens-label-inspector
Version: 0.2.14
Summary: 
Home-page: https://github.com/namehash/ens-label-inspector
License: MIT
Author: NameHash Team
Author-email: devops@namehash.io
Maintainer: NameHash Team
Maintainer-email: devops@namehash.io
Requires-Python: >=3.9,<3.13
Classifier: License :: OSI Approved :: MIT License
Classifier: Programming Language :: Python :: 3
Classifier: Programming Language :: Python :: 3.9
Classifier: Programming Language :: Python :: 3.10
Classifier: Programming Language :: Python :: 3.11
Classifier: Programming Language :: Python :: 3.12
Provides-Extra: lambda
Requires-Dist: emoji (>=2.8.0,<3.0.0)
Requires-Dist: ens-normalize (>=3.0.9,<4.0.0)
Requires-Dist: fastapi (>=0.115.4,<0.116.0)
Requires-Dist: hydra-core (>=1.3.2,<2.0.0)
Requires-Dist: mangum (>=0.17.0,<0.18.0) ; extra == "lambda"
Requires-Dist: more-itertools (>=10.1.0,<11.0.0)
Requires-Dist: regex (>=2024.11.6,<2025.0.0)
Project-URL: Repository, https://github.com/namehash/ens-label-inspector
